server_metrics/__init__.py
server_metrics/cpu.py
server_metrics/hard_disk.py
server_metrics/memcached.py
server_metrics/memory.py
server_metrics/postgresql.py
python_server_metrics-0.2.2.dist-info/AUTHORS
python_server_metrics-0.2.2.dist-info/LICENSE
python_server_metrics-0.2.2.dist-info/METADATA
python_server_metrics-0.2.2.dist-info/WHEEL
python_server_metrics-0.2.2.dist-info/top_level.txt
python_server_metrics-0.2.2.dist-info/RECORD
