Metadata-Version: 2.1
Name: python-server-metrics
Version: 0.2.2
Summary: A very simple set of methods to collect metrics about your servers
Home-page: https://github.com/bitmazk/python-server-metrics
Author: Martin Brochhaus
Author-email: mbrochh@gmail.com
License: The MIT License
Keywords: python,utility,metrics
Platform: OS Independent
License-File: LICENSE
License-File: AUTHORS
Requires-Dist: psutil
